apijet/__init__.py
apijet/main.py
apijet/version.py
apijet/commands/__init__.py
apijet/commands/create.py
apijet/commands/endpoint.py
apijet/commands/remove.py
apijet/templates/__init__.py
apijet/templates/app.template.py
apijet/templates/core.template.py
apijet/templates/core_db.template.py
apijet/templates/database.template.py
apijet/templates/dbmanager.template.py
apijet/templates/message_db.template.py
apijet/templates/model.template.py
apijet/templates/model_db.template.py
apijet/templates/project.template.py
apijet/templates/pyobjectid.template.py
apijet/templates/router.template.py
apijet/templates/router_db.template.py
apijet/utils/__init__.py
apijet/utils/opfile.py
apijet-0.5.1.dist-info/METADATA
apijet-0.5.1.dist-info/WHEEL
apijet-0.5.1.dist-info/entry_points.txt
apijet-0.5.1.dist-info/licenses/LICENSE
apijet-0.5.1.dist-info/RECORD
