Metadata-Version: 2.1
Name: apijet
Version: 0.5.1
Summary: A command line tool to deploy python Rest APIS in 20 secs.
Project-URL: Homepage, https://github.com/Arfius/apijet/
Project-URL: Bug Tracker, https://github.com/Arfius/apijet/issues
Author-email: Alfonso Farruggia <alfarruggia@gmail.com>
License-File: LICENSE
Classifier: License :: OSI Approved :: MIT License
Classifier: Operating System :: OS Independent
Classifier: Programming Language :: Python
Classifier: Programming Language :: Python :: 3
Classifier: Programming Language :: Python :: 3 :: Only
Classifier: Programming Language :: Python :: 3.8
Classifier: Programming Language :: Python :: 3.9
Classifier: Programming Language :: Python :: 3.10
Requires-Python: >=3.8
Requires-Dist: fastapi==0.85.0
Requires-Dist: gunicorn==20.1.0
Requires-Dist: pydantic==1.10.2
Requires-Dist: pymongo==4.2.0
Requires-Dist: starlette==0.20.4
Requires-Dist: uvicorn==0.18.3
